Metadata-Version: 2.1
Name: QMCM
Version: 0.0.0
Summary: This is an implementation of QMCM.
Author: Jay Sa
